open_next_cdk/__init__.py
open_next_cdk/py.typed
open_next_cdk/_jsii/__init__.py
open_next_cdk/_jsii/open-next-cdk@0.0.10.jsii.tgz
open_next_cdk-0.0.10.dist-info/LICENSE
open_next_cdk-0.0.10.dist-info/METADATA
open_next_cdk-0.0.10.dist-info/WHEEL
open_next_cdk-0.0.10.dist-info/top_level.txt
open_next_cdk-0.0.10.dist-info/RECORD
