Metadata-Version: 2.1
Name: open-next-cdk
Version: 0.0.10
Summary: Deploy a NextJS app using OpenNext packaging to serverless AWS using CDK
Home-page: https://github.com/datasprayio/open-next-cdk.git
Author: Dataspray<matus@matus.io>
License: Apache-2.0
Project-URL: Source, https://github.com/datasprayio/open-next-cdk.git
Classifier: Intended Audience :: Developers
Classifier: Operating System :: OS Independent
Classifier: Programming Language :: JavaScript
Classifier: Programming Language :: Python :: 3 :: Only
Classifier: Programming Language :: Python :: 3.7
Classifier: Programming Language :: Python :: 3.8
Classifier: Programming Language :: Python :: 3.9
Classifier: Programming Language :: Python :: 3.10
Classifier: Programming Language :: Python :: 3.11
Classifier: Typing :: Typed
Classifier: Development Status :: 5 - Production/Stable
Classifier: License :: OSI Approved
Requires-Python: ~=3.7
License-File: LICENSE
Requires-Dist: aws-cdk-lib <3.0.0,>=2.105.0
Requires-Dist: constructs <11.0.0,>=10.0.5
Requires-Dist: jsii <2.0.0,>=1.91.0
Requires-Dist: publication >=0.0.3
Requires-Dist: typeguard ~=2.13.3
